{"client":"Thunder Client","collectionName":"supermarket","dateExported":"2022-10-10T20:54:37.174Z","version":"1.1","folders":[{"_id":"763b5b56-9316-4427-b34f-988310a612da","name":"auth","containerId":"","created":"2022-09-29T01:42:40.325Z","sortNum":10000},{"_id":"1821eadb-8f86-405e-aa37-883df60d8784","name":"purchase","containerId":"","created":"2022-09-29T01:42:51.422Z","sortNum":20000},{"_id":"6d658e96-1535-4a6b-9825-b2cabeefa37e","name":"products","containerId":"","created":"2022-09-29T19:05:02.160Z","sortNum":30000},{"_id":"ae38ff7a-359d-4b5c-9dc4-aed79a7effd3","name":"user","containerId":"","created":"2022-10-07T13:52:23.900Z","sortNum":40000}],"requests":[{"_id":"84af27ba-b938-402b-bd4d-0fd464f31ddc","colId":"da025ddb-770d-4fda-8c4c-ffd32e8b243a","containerId":"763b5b56-9316-4427-b34f-988310a612da","name":"signup","url":"http://localhost:5000/signup","method":"POST","sortNum":10000,"created":"2022-09-28T22:21:42.319Z","modified":"2022-10-06T14:04:36.748Z","headers":[],"params":[],"body":{"type":"json","raw":"{\n  \"name\": \"leon\",\n  \"email\": \"test@gmail.com\",\n  \"password\": \"12345\",\n  \"confirmPassword\": \"12345\"\n}","form":[]},"tests":[]},{"_id":"dffbac73-7071-4c49-b466-39c2226eeaf5","colId":"da025ddb-770d-4fda-8c4c-ffd32e8b243a","containerId":"763b5b56-9316-4427-b34f-988310a612da","name":"signin","url":"http://localhost:5000/signin","method":"POST","sortNum":20000,"created":"2022-09-28T22:39:11.674Z","modified":"2022-09-29T01:42:43.262Z","headers":[],"params":[],"body":{"type":"json","raw":"{\n  \"email\": \"test@gmail.com\",\n  \"password\": \"12345\"\n}","form":[]},"tests":[]},{"_id":"92d0fb86-8723-4e19-aa8b-5503f3f66ce7","colId":"da025ddb-770d-4fda-8c4c-ffd32e8b243a","containerId":"1821eadb-8f86-405e-aa37-883df60d8784","name":"add_items_in_the_cart","url":"http://localhost:5000/cart/add","method":"POST","sortNum":30000,"created":"2022-09-29T01:43:07.948Z","modified":"2022-09-29T18:59:08.428Z","headers":[],"params":[],"body":{"type":"json","raw":"{\n  \"productId\": 4,\n  \"amount\": 2\n}","form":[]},"auth":{"type":"bearer","bearer":"eyJhbGciOiJIUzI1NiJ9.MQ.NiqkMTbY0gT45o8pqs9gjxBVOYayfaRqJZ4uHRJTJCo"},"tests":[]},{"_id":"a149bf8b-5c55-4b7b-ad96-6ce015b69dfb","colId":"da025ddb-770d-4fda-8c4c-ffd32e8b243a","containerId":"1821eadb-8f86-405e-aa37-883df60d8784","name":"remove_items_from_cart","url":"http://localhost:5000/cart/3","method":"DELETE","sortNum":40000,"created":"2022-09-29T18:31:41.672Z","modified":"2022-10-07T00:47:03.848Z","headers":[],"params":[],"auth":{"type":"bearer","bearer":"eyJhbGciOiJIUzI1NiJ9.MQ.NiqkMTbY0gT45o8pqs9gjxBVOYayfaRqJZ4uHRJTJCo"},"tests":[]},{"_id":"454a481a-c774-4fca-9111-b0932daa5653","colId":"da025ddb-770d-4fda-8c4c-ffd32e8b243a","containerId":"6d658e96-1535-4a6b-9825-b2cabeefa37e","name":"get_all_products","url":"http://localhost:5000/products","method":"GET","sortNum":50000,"created":"2022-09-29T19:05:14.438Z","modified":"2022-10-02T22:41:40.845Z","headers":[],"params":[],"auth":{"type":"bearer","bearer":"eyJhbGciOiJIUzI1NiJ9.MQ.NiqkMTbY0gT45o8pqs9gjxBVOYayfaRqJZ4uHRJTJCo"},"tests":[]},{"_id":"20cd7f3a-c1ac-4907-8fa0-711f3e51d5ea","colId":"da025ddb-770d-4fda-8c4c-ffd32e8b243a","containerId":"6d658e96-1535-4a6b-9825-b2cabeefa37e","name":"get_all_product_types","url":"http://localhost:5000/types","method":"GET","sortNum":60000,"created":"2022-09-29T19:24:17.111Z","modified":"2022-10-09T22:46:40.074Z","headers":[],"params":[],"auth":{"type":"bearer","bearer":"eyJhbGciOiJIUzI1NiJ9.MQ.NiqkMTbY0gT45o8pqs9gjxBVOYayfaRqJZ4uHRJTJCo"},"tests":[]},{"_id":"3631e8cc-df70-4dc7-89e8-4e5c53fec061","colId":"da025ddb-770d-4fda-8c4c-ffd32e8b243a","containerId":"6d658e96-1535-4a6b-9825-b2cabeefa37e","name":"get_products_by_type","url":"http://localhost:5000/products/1","method":"GET","sortNum":70000,"created":"2022-09-29T22:47:58.809Z","modified":"2022-10-01T22:48:21.337Z","headers":[],"params":[],"auth":{"type":"bearer"},"tests":[]},{"_id":"09a0e68d-af0c-4ff5-a5c4-817fe43c59b3","colId":"da025ddb-770d-4fda-8c4c-ffd32e8b243a","containerId":"1821eadb-8f86-405e-aa37-883df60d8784","name":"get_products_in_the_cart","url":"localhost:5000/cart/products","method":"GET","sortNum":80000,"created":"2022-10-03T15:44:34.747Z","modified":"2022-10-03T15:45:59.137Z","headers":[],"params":[],"auth":{"type":"bearer","bearer":"eyJhbGciOiJIUzI1NiJ9.MQ.NiqkMTbY0gT45o8pqs9gjxBVOYayfaRqJZ4uHRJTJCo"},"tests":[]},{"_id":"8ee92ab7-5a74-4b97-86af-03e87c3b368e","colId":"da025ddb-770d-4fda-8c4c-ffd32e8b243a","containerId":"6d658e96-1535-4a6b-9825-b2cabeefa37e","name":"get_products_by_name","url":"localhost:5000/products/name/Det","method":"GET","sortNum":100000,"created":"2022-10-05T13:14:37.677Z","modified":"2022-10-05T13:39:00.583Z","headers":[],"params":[],"tests":[]},{"_id":"82504f62-2b21-4c11-9c25-b6d045fcf0da","colId":"da025ddb-770d-4fda-8c4c-ffd32e8b243a","containerId":"ae38ff7a-359d-4b5c-9dc4-aed79a7effd3","name":"add_address","url":"http://localhost:5000/address","method":"POST","sortNum":110000,"created":"2022-10-07T13:52:34.406Z","modified":"2022-10-07T20:56:17.966Z","headers":[],"params":[],"body":{"type":"json","raw":"{\n  \"street\": \"rua dos araujos 3\",\n  \"number\": 35,\n  \"district\": \"frei higino\",\n  \"nickname\": \"casa 3\"\n}","form":[]},"auth":{"type":"bearer","bearer":"eyJhbGciOiJIUzI1NiJ9.Mg.gtPvNH3NvtcJ2f4r8gqHuw41OY7odany0iB31VRqx9c"},"tests":[]},{"_id":"aba3eef9-043b-43d1-a9ea-cebab679a907","colId":"da025ddb-770d-4fda-8c4c-ffd32e8b243a","containerId":"ae38ff7a-359d-4b5c-9dc4-aed79a7effd3","name":"get_user_addresses","url":"http://localhost:5000/address","method":"GET","sortNum":120000,"created":"2022-10-07T20:15:36.880Z","modified":"2022-10-07T20:15:49.635Z","headers":[],"params":[],"auth":{"type":"bearer","bearer":"eyJhbGciOiJIUzI1NiJ9.Mg.gtPvNH3NvtcJ2f4r8gqHuw41OY7odany0iB31VRqx9c"},"tests":[]},{"_id":"8d5048cb-3eab-4b4f-a468-18c7d4382dbd","colId":"da025ddb-770d-4fda-8c4c-ffd32e8b243a","containerId":"1821eadb-8f86-405e-aa37-883df60d8784","name":"create_purchase","url":"localhost:5000/purchase","method":"POST","sortNum":130000,"created":"2022-10-08T23:01:29.976Z","modified":"2022-10-08T23:18:32.591Z","headers":[],"params":[],"body":{"type":"json","raw":"{\n  \"total_price\": 10,\n  \"address_id\": 17\n}","form":[]},"auth":{"type":"bearer","bearer":"eyJhbGciOiJIUzI1NiJ9.MQ.NiqkMTbY0gT45o8pqs9gjxBVOYayfaRqJZ4uHRJTJCo"},"tests":[]},{"_id":"22d488a2-28c1-4725-845d-7446e877ae88","colId":"da025ddb-770d-4fda-8c4c-ffd32e8b243a","containerId":"1821eadb-8f86-405e-aa37-883df60d8784","name":"reset_cart","url":"localhost:5000/cart/reset","method":"POST","sortNum":140000,"created":"2022-10-08T23:41:19.894Z","modified":"2022-10-08T23:41:50.337Z","headers":[],"params":[],"auth":{"type":"bearer","bearer":"eyJhbGciOiJIUzI1NiJ9.MQ.NiqkMTbY0gT45o8pqs9gjxBVOYayfaRqJZ4uHRJTJCo"},"tests":[]},{"_id":"03877a5b-fca9-438f-a5e2-5f5def0abc4b","colId":"da025ddb-770d-4fda-8c4c-ffd32e8b243a","containerId":"1821eadb-8f86-405e-aa37-883df60d8784","name":"get_a_product_in_cart","url":"http://localhost:5000/cart/products/1","method":"GET","sortNum":150000,"created":"2022-10-10T20:51:17.926Z","modified":"2022-10-10T20:52:49.763Z","headers":[],"params":[],"auth":{"type":"bearer","bearer":"eyJhbGciOiJIUzI1NiJ9.Mg.gtPvNH3NvtcJ2f4r8gqHuw41OY7odany0iB31VRqx9c"},"tests":[]}]}
